hoborequest/__init__.py
hoborequest/gethobolink.py
hoborequest/hoboconfig.py
hoborequest/hoboconnect.py
hoborequest/conf/hobo-connect.conf-SAMPLE
hoborequest/conf/uva-arc.yaml
hoborequest/conf/loggers/20778368.yml
hoborequest/conf/loggers/20778369.yml
hoborequest/conf/sensors/20735863-1.yml
hoborequest/conf/sensors/20735863-B.yml
hoborequest/conf/sensors/20770097-1.yml
hoborequest/conf/sensors/20777744-1.yml
hoborequest/conf/sensors/20779676-1.yml
hoborequest/conf/sensors/micromet-station-CF-standard-names.txt
hoborequest/conf/sensors/templates/air_temperature.yml
hoborequest/conf/sensors/templates/gust_speed.yml
hoborequest/conf/sensors/templates/pressure.yml
hoborequest/conf/sensors/templates/rain.yml
hoborequest/conf/sensors/templates/relative_humidity.yml
hoborequest/conf/sensors/templates/solar_radiation.yml
hoborequest/conf/sensors/templates/wind_direction.yml
hoborequest/conf/sensors/templates/wind_speed.yml
hoborequest/lib/__init__.py
hoborequest/lib/hobo_config_import.py
hoborequest/lib/hobo_dtype.py
hoborequest/lib/hobo_link.py
hoborequest/lib/hobo_metadata.py
hoborequest/lib/hobo_time_util.py
hoborequest/tools/__init__.py
hoborequest/tools/check_dups.py
hoborequest/tools/check_gaps.py
hoborequest/tools/get_logger_sn.py
hoborequest/tools/get_root_attrs.py
hoborequest/tools/get_sensor_sn.py
hoborequest/tools/get_stats.py
hoborequest-1.1.data/data/conf/hobo-connect.conf-SAMPLE
hoborequest-1.1.data/data/conf/uva-arc.yaml
hoborequest-1.1.data/data/conf/loggers/20778368.yml
hoborequest-1.1.data/data/conf/loggers/20778369.yml
hoborequest-1.1.data/data/conf/sensors/20735863-1.yml
hoborequest-1.1.data/data/conf/sensors/20735863-B.yml
hoborequest-1.1.data/data/conf/sensors/20770097-1.yml
hoborequest-1.1.data/data/conf/sensors/20777744-1.yml
hoborequest-1.1.data/data/conf/sensors/20779676-1.yml
hoborequest-1.1.data/data/conf/sensors/templates/air_temperature.yml
hoborequest-1.1.data/data/conf/sensors/templates/gust_speed.yml
hoborequest-1.1.dist-info/licenses/LICENSE
hoborequest-1.1.dist-info/METADATA
hoborequest-1.1.dist-info/WHEEL
hoborequest-1.1.dist-info/entry_points.txt
hoborequest-1.1.dist-info/top_level.txt
hoborequest-1.1.dist-info/RECORD
