Metadata-Version: 2.4
Name: hoborequest
Version: 1.1
Summary: A Kubernetes-ready container application for integrating HOBOlink loggers with HSDS
Author-email: LF Murillo <lrosadom@nd.edu>, John Readey <jreadey@hdfgroup.org>
Maintainer-email: LF Murillo <lrosadom@nd.edu>, John Readey <jreadey@hdfgroup.org>
License-Expression: GPL-3.0-or-later
Project-URL: Source, https://gitlab.com/uva-arc/hobo-request
Project-URL: Release notes, https://gitlab.com/uva-arc/hobo-request/-/blob/main/CHANGELOG?ref_type=heads
Classifier: Environment :: Console
Classifier: Intended Audience :: Developers
Classifier: Intended Audience :: Science/Research
Classifier: Natural Language :: English
Classifier: Operating System :: POSIX :: Linux
Classifier: Operating System :: MacOS
Classifier: Programming Language :: Python :: 3
Classifier: Programming Language :: Python :: 3.10
Classifier: Programming Language :: Python :: 3.11
Classifier: Topic :: Internet :: WWW/HTTP :: HTTP Servers
Classifier: Topic :: Scientific/Engineering
Requires-Python: >=3.10
License-File: LICENSE
Requires-Dist: h5py>=3.12.1
Requires-Dist: h5pyd>=0.21.0
Requires-Dist: build==1.2.2.post1
Requires-Dist: certifi==2025.1.31
Requires-Dist: charset-normalizer==3.4.1
Requires-Dist: idna==3.10
Requires-Dist: numpy==2.2.2
Requires-Dist: packaging==24.2
Requires-Dist: PyJWT==2.10.1
Requires-Dist: pyproject_hooks==1.2.0
Requires-Dist: pytz==2025.1
Requires-Dist: requests==2.32.3
Requires-Dist: requests-unixsocket==0.3.0
Requires-Dist: requests_oauthlib==2.0.0
Requires-Dist: setuptools==75.8.0
Requires-Dist: urllib3==2.3.0
Requires-Dist: wheel==0.45.1
Requires-Dist: pyyaml==6.0.3
Dynamic: license-file
